{"matches_finished":[{"dw1":"","dw2":"","flag1":"https://x.boardgamearena.net/data/avatar/0/95/95814/95814549_184.jpg?h=a0eb4b3dfd","flag2":"https://x.boardgamearena.net/data/avatar/0/83/83925/83925004_184.jpg","format":"Bo3","group":"","gw1":"0","gw2":"2","id":"20251110-95814549-83925004","lineups":null,"opponent1_id":"95814549","opponent2_id":"83925004","rating":"3","round":"Quarterfinal: 10-11.Nov ","round_badge":"","stage":"Stage 2","status":"DONE","streamers":["https://carcassonne.gg/gallery/stream_alexey.png"],"streams":["https://youtube.com/live/srm9ceo_19g?feature=share"],"team1":"Licinio Ferreira","team2":"Sportr","time":"10.11.2025 22:00:00","tournament":"Portuguese CCL Qualifier","tournament_id":"PTCCLQ-2025","tournament_link":"https://carcassonne.gg/PTCCLQ-2025/?tab=stage2","tournament_logo":"https://carcassonne.gg/gallery/portugal-logo-small.png","tournament_type":"COC"},{"dw1":"","dw2":"","flag1":"https://x.boardgamearena.net/data/avatar/defaults/default-2401.jpg","flag2":"https://x.boardgamearena.net/data/avatar/0/85/85119/85119891_184.jpg","format":"Bo3","group":"","gw1":"2","gw2":"1","id":"20251110-85217439-85119891","lineups":null,"opponent1_id":"85217439","opponent2_id":"85119891","rating":"3","round":"Quarterfinal: 10-11.Nov ","round_badge":"","stage":"Stage 2","status":"DONE","streamers":["https://carcassonne.gg/gallery/stream_alexey.png"],"streams":["https://youtube.com/live/srm9ceo_19g?feature=share"],"team1":"JMargarido","team2":"sisi","time":"10.11.2025 21:00:00","tournament":"Portuguese CCL Qualifier","tournament_id":"PTCCLQ-2025","tournament_link":"https://carcassonne.gg/PTCCLQ-2025/?tab=stage2","tournament_logo":"https://carcassonne.gg/gallery/portugal-logo-small.png","tournament_type":"COC"},{"dw1":"","dw2":"","flag1":"https://x.boardgamearena.net/data/avatar/0/84/84972/84972043_184.jpg","flag2":"https://x.boardgamearena.net/data/avatar/0/85/85573/85573257_184.jpg","format":"Bo3","group":"","gw1":"2","gw2":"1","id":"20251109-84972043-85573257","lineups":null,"opponent1_id":"84972043","opponent2_id":"85573257","rating":"5","round":"Final","round_badge":"","stage":"Stage 2","status":"DONE","streamers":[],"streams":[],"team1":"LazyBore","team2":"FanaticalLime93","time":"09.11.2025 21:00:00","tournament":"UK Carcassonne Online Championship 2025","tournament_id":"UKOC-2025","tournament_link":"https://carcassonne.gg/UKOC-2025/?tab=stage2","tournament_logo":"https://carcassonne.uk/images/carcuk.png","tournament_type":"COC"},{"dw1":"","dw2":"","flag1":"https://x.boardgamearena.net/data/avatar/0/85/85573/85573257_184.jpg","flag2":"https://x.boardgamearena.net/data/avatar/0/92/92216/92216740_184.jpg","format":"Bo3","group":"","gw1":"2","gw2":"0","id":"20251109-85573257-92216740","lineups":null,"opponent1_id":"85573257","opponent2_id":"92216740","rating":"4","round":"Semifinal","round_badge":"","stage":"Stage 2","status":"DONE","streamers":["https://carcassonne.gg/gallery/stream_alexey.png"],"streams":["https://youtube.com/live/_uiAhxq1YBk?feature=share"],"team1":"FanaticalLime93","team2":"OJH1997","time":"09.11.2025 10:00:00","tournament":"UK Carcassonne Online Championship 2025","tournament_id":"UKOC-2025","tournament_link":"https://carcassonne.gg/UKOC-2025/?tab=stage2","tournament_logo":"https://carcassonne.uk/images/carcuk.png","tournament_type":"COC"},{"dw1":"","dw2":"","flag1":"https://x.boardgamearena.net/data/avatar/0/84/84972/84972043_184.jpg","flag2":"https://x.boardgamearena.net/data/avatar/0/94/94433/94433733_184.jpg","format":"Bo3","group":"","gw1":"2","gw2":"1","id":"20251107-84972043-94433733","lineups":null,"opponent1_id":"84972043","opponent2_id":"94433733","rating":"5","round":"Semifinal","round_badge":"","stage":"Stage 2","status":"DONE","streamers":["https://carcassonne.gg/gallery/stream_alexey.png"],"streams":["https://youtube.com/live/JCZWAGNfCrY?feature=share"],"team1":"LazyBore","team2":"Lord Terrycloth","time":"07.11.2025 17:00:00","tournament":"UK Carcassonne Online Championship 2025","tournament_id":"UKOC-2025","tournament_link":"https://carcassonne.gg/UKOC-2025/?tab=stage2","tournament_logo":"https://carcassonne.uk/images/carcuk.png","tournament_type":"COC"},{"dw1":"","dw2":"","flag1":"https://x.boardgamearena.net/data/avatar/defaults/default-1185.jpg","flag2":"https://x.boardgamearena.net/data/avatar/0/84/84616/84616793_184.jpg?h=3f26ed3c4d","format":"Bo3","group":"","gw1":"2","gw2":"1","id":"20251105-88803329-84616793","lineups":null,"opponent1_id":"88803329","opponent2_id":"84616793","rating":"3","round":"Round 11","round_badge":"","stage":"Stage 1","status":"DONE","streamers":[],"streams":[],"team1":"Simaster 1991","team2":"Hurtle_cz","time":"05.11.2025 20:00:00","tournament":"Czech Online National Championship 2025","tournament_id":"CZ-2025-COC","tournament_link":"https://carcassonne.gg/CZ-2025-COC?tab=stage1","tournament_logo":"https://carcassonne.gg/gallery_gen/f8541fc1f159d205ca9c40208c0d568f_170x170_fit.jpg","tournament_type":"COC"},{"dw1":"","dw2":"","flag1":"https://x.boardgamearena.net/data/avatar/defaults/default-1130.jpg","flag2":"https://x.boardgamearena.net/data/avatar/0/84/84616/84616793_184.jpg?h=3f26ed3c4d","format":"Bo3","group":"","gw1":"1","gw2":"2","id":"20251104-88295846-84616793","lineups":null,"opponent1_id":"88295846","opponent2_id":"84616793","rating":"2","round":"Round 10","round_badge":"","stage":"Stage 1","status":"DONE","streamers":[],"streams":[],"team1":"soustruznice","team2":"Hurtle_cz","time":"04.11.2025 18:00:00","tournament":"Czech Online National Championship 2025","tournament_id":"CZ-2025-COC","tournament_link":"https://carcassonne.gg/CZ-2025-COC?tab=stage1","tournament_logo":"https://carcassonne.gg/gallery_gen/f8541fc1f159d205ca9c40208c0d568f_170x170_fit.jpg","tournament_type":"COC"}],"matches_scheduled":[{"dw1":"","dw2":"","flag1":"https://x.boardgamearena.net/data/avatar/defaults/default-2401.jpg","flag2":"https://x.boardgamearena.net/data/avatar/0/83/83925/83925004_184.jpg","format":"Bo3","group":"","gw1":"","gw2":"","id":"20251112-85217439-83925004","lineups":null,"opponent1_id":"85217439","opponent2_id":"83925004","rating":"5","round":"Semifinal: 12-13.Nov ","round_badge":"","stage":"Stage 2","status":"PLANED","streamers":[],"streams":[],"team1":"JMargarido","team2":"Sportr","time":"12.11.2025 14:00:00","tournament":"Portuguese CCL Qualifier","tournament_id":"PTCCLQ-2025","tournament_link":"https://carcassonne.gg/PTCCLQ-2025/?tab=stage2","tournament_logo":"https://carcassonne.gg/gallery/portugal-logo-small.png","tournament_type":"COC"},{"dw1":"","dw2":"","flag1":"https://x.boardgamearena.net/data/avatar/0/94/94346/94346145_184.jpg?h=98fcdc93fb","flag2":"https://x.boardgamearena.net/data/avatar/0/85/85447/85447228_184.jpg","format":"Bo3","group":"","gw1":"","gw2":"","id":"20251112-94346145-85447228","lineups":null,"opponent1_id":"94346145","opponent2_id":"85447228","rating":"5","round":"Semifinal: 12-13.Nov ","round_badge":"","stage":"Stage 2","status":"PLANED","streamers":[],"streams":[],"team1":"phoam","team2":"Glovir","time":"12.11.2025 21:30:00","tournament":"Portuguese CCL Qualifier","tournament_id":"PTCCLQ-2025","tournament_link":"https://carcassonne.gg/PTCCLQ-2025/?tab=stage2","tournament_logo":"https://carcassonne.gg/gallery/portugal-logo-small.png","tournament_type":"COC"}],"matches_today":[{"dw1":"","dw2":"","flag1":"https://x.boardgamearena.net/data/avatar/0/94/94346/94346145_184.jpg?h=98fcdc93fb","flag2":"https://x.boardgamearena.net/data/avatar/0/84/84757/84757617_184.jpg","format":"Bo3","group":"","gw1":"2","gw2":"0","id":"20251111-94346145-84757617","lineups":null,"opponent1_id":"94346145","opponent2_id":"84757617","rating":"4","round":"Quarterfinal: 10-11.Nov ","round_badge":"","stage":"Stage 2","status":"DONE","streamers":["https://carcassonne.gg/gallery/stream_nallerheim.png"],"streams":["https://youtube.com/live/SIIHQEGCilY?feature=share"],"team1":"phoam","team2":"Mestre77","time":"11.11.2025 09:00:00","tournament":"Portuguese CCL Qualifier","tournament_id":"PTCCLQ-2025","tournament_link":"https://carcassonne.gg/PTCCLQ-2025/?tab=stage2","tournament_logo":"https://carcassonne.gg/gallery/portugal-logo-small.png","tournament_type":"COC"},{"dw1":"","dw2":"","flag1":"https://x.boardgamearena.net/data/avatar/0/85/85379/85379310_184.jpg","flag2":"https://x.boardgamearena.net/data/avatar/defaults/default-0045.jpg","format":"Bo3","group":"","gw1":"2","gw2":"0","id":"20251111-85379310-88500055","lineups":null,"opponent1_id":"85379310","opponent2_id":"88500055","rating":"5","round":"Round 10","round_badge":"","stage":"Stage 1","status":"DONE","streamers":[],"streams":[],"team1":"martypartyouje","team2":"majkls","time":"11.11.2025 17:00:00","tournament":"Czech Online National Championship 2025","tournament_id":"CZ-2025-COC","tournament_link":"https://carcassonne.gg/CZ-2025-COC?tab=stage1","tournament_logo":"https://carcassonne.gg/gallery_gen/f8541fc1f159d205ca9c40208c0d568f_170x170_fit.jpg","tournament_type":"COC"},{"dw1":"","dw2":"","flag1":"https://x.boardgamearena.net/data/avatar/0/85/85447/85447228_184.jpg","flag2":"https://x.boardgamearena.net/data/avatar/0/97/97284/97284253_184.jpg","format":"Bo3","group":"","gw1":"2","gw2":"0","id":"20251111-85447228-97284253","lineups":null,"opponent1_id":"85447228","opponent2_id":"97284253","rating":"5","round":"Quarterfinal: 10-11.Nov ","round_badge":"","stage":"Stage 2","status":"DONE","streamers":["https://carcassonne.gg/gallery/stream_nallerheim.png"],"streams":["https://youtube.com/live/v3S9kRrBlOg?feature=share"],"team1":"Glovir","team2":"notnewatthis","time":"11.11.2025 21:30:00","tournament":"Portuguese CCL Qualifier","tournament_id":"PTCCLQ-2025","tournament_link":"https://carcassonne.gg/PTCCLQ-2025/?tab=stage2","tournament_logo":"https://carcassonne.gg/gallery/portugal-logo-small.png","tournament_type":"COC"}],"status":"success","tournaments_finished":[{"link":"https://carcassonne.gg/PTCCLQ-2025/?tab=stage2","logo":"https://carcassonne.gg/gallery/portugal-logo-small.png","name":"Portuguese CCL Qualifier","type":"COC"},{"link":"https://carcassonne.gg/UKOC-2025/?tab=stage2","logo":"https://carcassonne.uk/images/carcuk.png","name":"UK Carcassonne Online Championship 2025","type":"COC"},{"link":"https://carcassonne.gg/CZ-2025-COC?tab=stage1","logo":"https://carcassonne.gg/gallery_gen/f8541fc1f159d205ca9c40208c0d568f_170x170_fit.jpg","name":"Czech Online National Championship 2025","type":"COC"}],"tournaments_scheduled":[{"link":"https://carcassonne.gg/PTCCLQ-2025/?tab=stage2","logo":"https://carcassonne.gg/gallery/portugal-logo-small.png","name":"Portuguese CCL Qualifier","type":"COC"}],"tournaments_today":[{"link":"https://carcassonne.gg/PTCCLQ-2025/?tab=stage2","logo":"https://carcassonne.gg/gallery/portugal-logo-small.png","name":"Portuguese CCL Qualifier","type":"COC"},{"link":"https://carcassonne.gg/CZ-2025-COC?tab=stage1","logo":"https://carcassonne.gg/gallery_gen/f8541fc1f159d205ca9c40208c0d568f_170x170_fit.jpg","name":"Czech Online National Championship 2025","type":"COC"}]}
